bigbluepy/__init__.py
bigbluepy/main.py
bigbluepy/requests.py
bigbluepy/response/__init__.py
bigbluepy/response/create_meeting.py
bigbluepy/response/end_meeting.py
bigbluepy/response/is_meeting_running.py
bigbluepy/response/join_meeting.py
bigbluepy/response/meeting_info.py
bigbluepy/response/meetings.py
examples/__init__.py
examples/getMeetings.py
bigbluepy-0.1.8.dist-info/METADATA
bigbluepy-0.1.8.dist-info/WHEEL
bigbluepy-0.1.8.dist-info/top_level.txt
bigbluepy-0.1.8.dist-info/RECORD
