Metadata-Version: 2.1
Name: bigbluepy
Version: 0.1.8
Summary: An unofficial Bigbluebutton api.
Home-page: https://github.com/its0x4d/bigbluepython-python
Author: UWSGI
Author-email: mosydev2016@gmail.com
License: MIT
Platform: any
Classifier: Programming Language :: Python :: 3
Classifier: License :: OSI Approved :: MIT License
Classifier: Operating System :: OS Independent
Requires-Dist: packaging
Requires-Dist: xmltodict
Requires-Dist: requests
